README.rst
setup.py
ddd_domain_events/__init__.py
ddd_domain_events/domain_event_callable.py
ddd_domain_events/domain_events.py
ddd_domain_events.egg-info/PKG-INFO
ddd_domain_events.egg-info/SOURCES.txt
ddd_domain_events.egg-info/dependency_links.txt
ddd_domain_events.egg-info/not-zip-safe
ddd_domain_events.egg-info/top_level.txt