Metadata-Version: 1.1
Name: ddd-domain-events
Version: 0.1.4
Summary: ['Domain Driven Design: ', 'implementation of in memory Cross Cutting domain events infrastructure.']
Home-page: https://gitlab.com/py-ddd/ddd-domain-events
Author: Victor Klapholz
Author-email: victor.klapholz@gmail.com
License: MIT
Keywords: Domain Driven Design,Design Patterns,DDD,Domain Events,Strategic DDD Patterns
Platform: UNKNOWN
Classifier: Development Status :: 5 - Production/Stable
Classifier: Intended Audience :: Developers
Classifier: License :: OSI Approved :: MIT License
Classifier: Programming Language :: Python :: 3.6
Classifier: Programming Language :: Python :: Implementation :: CPython
Classifier: Programming Language :: Python :: Implementation :: PyPy
